Lab1/OneBitAdder.v
module OneBitAdder (
  // Inputs.
  input x,
  input y,
  input carry_in,

  // Outputs.
  output sum,
  output carry_out
);
    // Description of the logic goes here.
    wire x_not;
    wire y_not;
    wire carry_in_not;
    wire i1, i2, i3, i4, i5, i6, i7, i8, i9, i10;

    assign x_not = ~x;
    assign y_not = ~y;
    assign carry_in_not = ~carry_in;

    // Let's describe circuit for sum.
    assign i1 = x_not & y_not;
    assign i5 = carry_in & i1;

    assign i2 = x_not & y;
    assign i6 = carry_in_not & i2;

    assign i3 = x & y_not;
    assign i7 = carry_in_not & i3;

    assign i4 = x & y;
    assign i8 = carry_in & i4;

    assign i9 = i5 | i6;
    assign i10 = i7 | i8;

    assign sum = i9 | i10;

    // Carry out description.
    assign carry_out = (x & carry_in) | (y & carry_in) | (x & y);

endmodule

Lab1/one_bit_adder.vcd
$version Generated by VerilatedVcd $end
$date Sun Feb 20 23:00:18 2022
 $end
$timescale   1ns $end

 $scope module TOP $end
  $var wire  1 3 carry_in $end
  $var wire  1 C carry_out $end
  $var wire  1 ; sum $end
  $var wire  1 # x $end
  $var wire  1 + y $end
  $scope module OneBitAdder $end
   $var wire  1 3 carry_in $end
   $var wire  1 [ carry_in_not $end
   $var wire  1 C carry_out $end
   $var wire  1 c i1 $end
   $var wire  1 M! i10 $end
   $var wire  1 k i2 $end
   $var wire  1 s i3 $end
   $var wire  1 { i4 $end
   $var wire  1 %! i5 $end
   $var wire  1 -! i6 $end
   $var wire  1 5! i7 $end
   $var wire  1 =! i8 $end
   $var wire  1 E! i9 $end
   $var wire  1 ; sum $end
   $var wire  1 # x $end
   $var wire  1 K x_not $end
   $var wire  1 + y $end
   $var wire  1 S y_not $end
  $upscope $end
 $upscope $end
$enddefinitions $end


#0
1#
0+
13
0;
1C
0K
1S
0[
0c
0k
1s
0{
0%!
0-!
05!
0=!
0E!
0M!
#1
#1
1+
1;
0S
0s
1{
1=!
1M!
#2
#2
0#
0+
0C
1K
1S
1c
0{
1%!
0=!
1E!
0M!
#3
#3
1#
0;
1C
0K
0c
1s
0%!
0E!
#4
#4
0#
1+
1K
0S
1k
0s
#5
#5
0+
03
0C
1S
1[
1c
0k
#6
#6
13
1;
0[
1%!
1E!
#7
#7
1+
0;
1C
0S
0c
1k
0%!
0E!
#8
#8
0+
03
0C
1S
1[
1c
0k
#9
#9
1#
1+
13
1;
1C
0K
0S
0[
0c
1{
1=!
1M!
#10
#10
0+
03
0C
1S
1[
1s
0{
15!
0=!
#11
#11
0#
1+
13
0;
1C
1K
0S
0[
1k
0s
05!
0M!
#12
#12
1#
0+
0K
1S
0k
1s
#13
#13
0#
1+
1K
0S
1k
0s
#14
#14
1#
03
0K
1[
0k
1{
#15
#15
0+
1;
0C
1S
1s
0{
15!
1M!
#16
#16
13
0;
1C
0[
05!
0M!
#17
#17
0#
1+
03
1;
0C
1K
0S
1[
1k
0s
1-!
1E!
#18
#18
#19
#19
0+
13
1S
0[
1c
0k
1%!
0-!
#20
#20
1#
1+
03
0;
1C
0K
0S
1[
0c
1{
0%!
0E!
#21
#21
0+
13
1S
0[
1s
0{
#22
#22
0#
1+
1K
0S
1k
0s
#23
#23
1#
0+
0K
1S
0k
1s
#24
#24
0#
1+
03
1;
0C
1K
0S
1[
1k
0s
1-!
1E!
#25
#25
1#
0+
0K
1S
0k
1s
0-!
15!
0E!
1M!
#26
#26
13
0;
1C
0[
05!
0M!
#27
#27
0#
03
0C
1K
1[
1c
0s
#28
#28
13
1;
0[
1%!
1E!
#29
#29
1#
0;
1C
0K
0c
1s
0%!
0E!
#30
#30
0#
03
0C
1K
1[
1c
0s
#31
#31
1+
1;
0S
0c
1k
1-!
1E!
#32
#32
0+
0;
1S
1c
0k
0-!
0E!
#33
#33
1#
1+
1C
0K
0S
0c
1{
#34
#34
0#
0+
13
1;
0C
1K
1S
0[
1c
0{
1%!
1E!
#35
#35
1#
1+
03
0;
1C
0K
0S
1[
0c
1{
0%!
0E!
#36
#36
0+
1;
0C
1S
1s
0{
15!
1M!
#37
#37
0#
1+
1K
0S
1k
0s
1-!
05!
1E!
0M!
#38
#38
13
0;
1C
0[
0-!
0E!
#39
#39
1#
0+
0K
1S
0k
1s
#40
#40
0#
1+
1K
0S
1k
0s
#41
#41
1#
1;
0K
0k
1{
1=!
1M!
#42
#42
#43
#43
03
0;
1[
0=!
0M!
#44
#44
#45
#45
0+
13
1S
0[
1s
0{
#46
#46
03
1;
0C
1[
15!
1M!
#47
#47
13
0;
1C
0[
05!
0M!
#48
#48
1+
03
0S
1[
0s
1{
#49
#49
0#
0+
13
1;
0C
1K
1S
0[
1c
0{
1%!
1E!
#50
#50
1+
03
0S
1[
0c
1k
0%!
1-!
#51
#51
1#
0+
13
0;
1C
0K
1S
0[
0k
1s
0-!
0E!
#52
#52
0#
1+
1K
0S
1k
0s
#53
#53
1#
03
0K
1[
0k
1{
#54
#54
0#
0+
13
1;
0C
1K
1S
0[
1c
0{
1%!
1E!
#55
#55
1+
03
0S
1[
0c
1k
0%!
1-!
#56
#56
0+
0;
1S
1c
0k
0-!
0E!
#57
#57
1+
1;
0S
0c
1k
1-!
1E!
#58
#58
1#
13
1C
0K
0[
0k
1{
0-!
1=!
0E!
1M!
#59
#59
03
0;
1[
0=!
0M!
#60
#60
0#
13
1K
0[
1k
0{
#61
#61
#62
#62
03
1;
0C
1[
1-!
1E!
#63
#63
1#
13
1C
0K
0[
0k
1{
0-!
1=!
0E!
1M!
#64
#64
03
0;
1[
0=!
0M!
#65
#65
0#
13
1K
0[
1k
0{
#66
#66
03
1;
0C
1[
1-!
1E!
#67
#67
13
0;
1C
0[
0-!
0E!
#68
#68
1#
0+
03
1;
0C
0K
1S
1[
0k
1s
15!
1M!
#69
#69
0#
0;
1K
1c
0s
05!
0M!
#70
#70
13
1;
0[
1%!
1E!
#71
#71
1#
1+
03
0;
1C
0K
0S
1[
0c
1{
0%!
0E!
#72
#72
0#
1;
0C
1K
1k
0{
1-!
1E!
#73
#73
1#
0+
13
0;
1C
0K
1S
0[
0k
1s
0-!
0E!
#74
#74
0#
1+
03
1;
0C
1K
0S
1[
1k
0s
1-!
1E!
#75
#75
13
0;
1C
0[
0-!
0E!
#76
#76
0+
1;
0C
1S
1c
0k
1%!
1E!
#77
#77
03
0;
1[
0%!
0E!
#78
#78
1#
1+
13
1;
1C
0K
0S
0[
0c
1{
1=!
1M!
#79
#79
0#
0+
0C
1K
1S
1c
0{
1%!
0=!
1E!
0M!
#80
#80
#81
#81
1#
03
0K
1[
0c
1s
0%!
15!
0E!
1M!
#82
#82
0#
13
1K
0[
1c
0s
1%!
05!
1E!
0M!
#83
#83
1+
0;
1C
0S
0c
1k
0%!
0E!
#84
#84
1#
0+
03
1;
0C
0K
1S
1[
0k
1s
15!
1M!
#85
#85
#86
#86
0#
0;
1K
1c
0s
05!
0M!
#87
#87
1#
1;
0K
0c
1s
15!
1M!
#88
#88
0#
0;
1K
1c
0s
05!
0M!
#89
#89
1#
1;
0K
0c
1s
15!
1M!
#90
#90
0#
0;
1K
1c
0s
05!
0M!
#91
#91
1#
1+
1C
0K
0S
0c
1{
#92
#92
0#
13
1K
0[
1k
0{
#93
#93
1#
03
0K
1[
0k
1{
#94
#94
0+
1;
0C
1S
1s
0{
15!
1M!
#95
#95
1+
13
1C
0S
0[
0s
1{
05!
1=!
#96
#96
0+
0;
1S
1s
0{
0=!
0M!
#97
#97
1+
03
0S
1[
0s
1{
#98
#98
0#
1;
0C
1K
1k
0{
1-!
1E!
#99
#99
0+
0;
1S
1c
0k
0-!
0E!
#100
#100
#101
#101
13
1;
0[
1%!
1E!
#102
#102
1#
0;
1C
0K
0c
1s
0%!
0E!
#103
#103
0#
1+
03
1;
0C
1K
0S
1[
1k
0s
1-!
1E!
#104
#104
0+
13
1S
0[
1c
0k
1%!
0-!
#105
#105
1#
03
0K
1[
0c
1s
0%!
15!
0E!
1M!
#106
#106
0#
1+
1K
0S
1k
0s
1-!
05!
1E!
0M!
#107
#107
1#
0;
1C
0K
0k
1{
0-!
0E!
#108
#108
13
1;
0[
1=!
1M!
#109
#109
03
0;
1[
0=!
0M!
#110
#110
#111
#111
#112
#112
0+
1;
0C
1S
1s
0{
15!
1M!
#113
#113
0#
0;
1K
1c
0s
05!
0M!
#114
#114
1+
1;
0S
0c
1k
1-!
1E!
#115
#115
1#
0+
0K
1S
0k
1s
0-!
15!
0E!
1M!
#116
#116
0#
0;
1K
1c
0s
05!
0M!
#117
#117
1+
13
1C
0S
0[
0c
1k
#118
#118
03
1;
0C
1[
1-!
1E!
#119
#119
0+
13
1S
0[
1c
0k
1%!
0-!
#120
#120
03
0;
1[
0%!
0E!
#121
#121
1+
13
1C
0S
0[
0c
1k
#122
#122
1#
0+
03
1;
0C
0K
1S
1[
0k
1s
15!
1M!
#123
#123
#124
#124
1+
13
1C
0S
0[
0s
1{
05!
1=!
#125
#125
0#
0+
0C
1K
1S
1c
0{
1%!
0=!
1E!
0M!
#126
#126
#127
#127
1+
0;
1C
0S
0c
1k
0%!
0E!
#128
#128
1#
03
0K
1[
0k
1{
#129
#129
#130
#130
0#
1;
0C
1K
1k
0{
1-!
1E!
#131
#131
0+
0;
1S
1c
0k
0-!
0E!
#132
#132
1+
1;
0S
0c
1k
1-!
1E!
#133
#133
0+
13
1S
0[
1c
0k
1%!
0-!
#134
#134
03
0;
1[
0%!
0E!
#135
#135
#136
#136
1#
13
1C
0K
0[
0c
1s
#137
#137
1+
03
0S
1[
0s
1{
#138
#138
0#
0+
13
1;
0C
1K
1S
0[
1c
0{
1%!
1E!
#139
#139
#140
#140
03
0;
1[
0%!
0E!
#141
#141
1#
1+
1C
0K
0S
0c
1{
#142
#142
13
1;
0[
1=!
1M!
#143
#143
03
0;
1[
0=!
0M!
#144
#144
0#
1;
0C
1K
1k
0{
1-!
1E!
#145
#145
#146
#146
1#
0;
1C
0K
0k
1{
0-!
0E!
#147
#147
0#
0+
13
1;
0C
1K
1S
0[
1c
0{
1%!
1E!
#148
#148
03
0;
1[
0%!
0E!
#149
#149
1#
1;
0K
0c
1s
15!
1M!
#150
#150
0#
0;
1K
1c
0s
05!
0M!
#151
#151
1#
1+
13
1;
1C
0K
0S
0[
0c
1{
1=!
1M!
#152
#152
0+
03
0C
1S
1[
1s
0{
15!
0=!
#153
#153
13
0;
1C
0[
05!
0M!
#154
#154
#155
#155
1+
03
0S
1[
0s
1{
#156
#156
0+
13
1S
0[
1s
0{
#157
#157
#158
#158
#159
#159
1+
1;
0S
0s
1{
1=!
1M!
#160
#160
0+
03
0C
1S
1[
1s
0{
15!
0=!
#161
#161
1+
13
1C
0S
0[
0s
1{
05!
1=!
#162
#162
0+
03
0C
1S
1[
1s
0{
15!
0=!
#163
#163
1+
0;
1C
0S
0s
1{
05!
0M!
#164
#164
0+
1;
0C
1S
1s
0{
15!
1M!
#165
#165
0#
1+
13
0;
1C
1K
0S
0[
1k
0s
05!
0M!
#166
#166
0+
1;
0C
1S
1c
0k
1%!
1E!
#167
#167
#168
#168
1#
1+
1C
0K
0S
0c
1{
0%!
1=!
0E!
1M!
#169
#169
0+
0;
1S
1s
0{
0=!
0M!
#170
#170
0#
1+
1K
0S
1k
0s
#171
#171
0+
03
0C
1S
1[
1c
0k
#172
#172
1+
1;
0S
0c
1k
1-!
1E!
#173
#173
#174
#174
0+
0;
1S
1c
0k
0-!
0E!
#175
#175
#176
#176
#177
#177
1#
1;
0K
0c
1s
15!
1M!
#178
#178
13
0;
1C
0[
05!
0M!
#179
#179
0#
1+
1K
0S
1k
0s
#180
#180
1#
03
0K
1[
0k
1{
#181
#181
0#
0+
13
1;
0C
1K
1S
0[
1c
0{
1%!
1E!
#182
#182
03
0;
1[
0%!
0E!
#183
#183
1#
13
1C
0K
0[
0c
1s
#184
#184
#185
#185
#186
#186
03
1;
0C
1[
15!
1M!
#187
#187
0#
0;
1K
1c
0s
05!
0M!
#188
#188
1+
1;
0S
0c
1k
1-!
1E!
#189
#189
13
0;
1C
0[
0-!
0E!
#190
#190
1#
1;
0K
0k
1{
1=!
1M!
#191
#191
0#
0;
1K
1k
0{
0=!
0M!
#192
#192
1#
0+
0K
1S
0k
1s
#193
#193
1+
1;
0S
0s
1{
1=!
1M!
#194
#194
0+
0;
1S
1s
0{
0=!
0M!
#195
#195
0#
1+
1K
0S
1k
0s
#196
#196
03
1;
0C
1[
1-!
1E!
#197
#197
#198
#198
13
0;
1C
0[
0-!
0E!
#199
#199
1#
03
0K
1[
0k
1{
#200
#200
0#
13
1K
0[
1k
0{
#201
#201
1#
1;
0K
0k
1{
1=!
1M!
#202
#202
0#
0+
0C
1K
1S
1c
0{
1%!
0=!
1E!
0M!
#203
#203
1#
1+
03
0;
1C
0K
0S
1[
0c
1{
0%!
0E!
#204
#204
0#
0+
0C
1K
1S
1c
0{
#205
#205
1#
1+
13
1;
1C
0K
0S
0[
0c
1{
1=!
1M!
#206
#206
03
0;
1[
0=!
0M!
#207
#207
13
1;
0[
1=!
1M!
#208
#208
#209
#209
0#
0+
03
0;
0C
1K
1S
1[
1c
0{
0=!
0M!
#210
#210
1+
13
1C
0S
0[
0c
1k
#211
#211
0+
03
0C
1S
1[
1c
0k
#212
#212
1#
1+
1C
0K
0S
0c
1{
#213
#213
0#
0+
0C
1K
1S
1c
0{
#214
#214
1+
1;
0S
0c
1k
1-!
1E!
#215
#215
0+
13
1S
0[
1c
0k
1%!
0-!
#216
#216
1#
1+
03
0;
1C
0K
0S
1[
0c
1{
0%!
0E!
#217
#217
0#
0+
13
1;
0C
1K
1S
0[
1c
0{
1%!
1E!
#218
#218
1#
1+
1C
0K
0S
0c
1{
0%!
1=!
0E!
1M!
#219
#219
0#
0;
1K
1k
0{
0=!
0M!
#220
#220
1#
0+
03
1;
0C
0K
1S
1[
0k
1s
15!
1M!
#221
#221
0#
13
1K
0[
1c
0s
1%!
05!
1E!
0M!
#222
#222
1#
1+
03
0;
1C
0K
0S
1[
0c
1{
0%!
0E!
#223
#223
#224
#224
13
1;
0[
1=!
1M!
#225
#225
0#
03
0C
1K
1[
1k
0{
1-!
0=!
1E!
0M!
#226
#226
1#
0+
13
0;
1C
0K
1S
0[
0k
1s
0-!
0E!
#227
#227
0#
03
0C
1K
1[
1c
0s
#228
#228
1#
13
1C
0K
0[
0c
1s
#229
#229
0#
1;
0C
1K
1c
0s
1%!
1E!
#230
#230
1+
0;
1C
0S
0c
1k
0%!
0E!
#231
#231
0+
1;
0C
1S
1c
0k
1%!
1E!
#232
#232
1#
1+
03
0;
1C
0K
0S
1[
0c
1{
0%!
0E!
#233
#233
0+
13
1S
0[
1s
0{
#234
#234
0#
03
0C
1K
1[
1c
0s
#235
#235
1#
13
1C
0K
0[
0c
1s
#236
#236
1+
1;
0S
0s
1{
1=!
1M!
#237
#237
03
0;
1[
0=!
0M!
#238
#238
#239
#239
0#
1;
0C
1K
1k
0{
1-!
1E!
#240
#240
1#
0;
1C
0K
0k
1{
0-!
0E!
#241
#241
0#
0+
0C
1K
1S
1c
0{
#242
#242
1#
1+
13
1;
1C
0K
0S
0[
0c
1{
1=!
1M!
#243
#243
#244
#244
0#
0;
1K
1k
0{
0=!
0M!
#245
#245
0+
1;
0C
1S
1c
0k
1%!
1E!
#246
#246
1#
0;
1C
0K
0c
1s
0%!
0E!
#247
#247
1+
03
0S
1[
0s
1{
#248
#248
0+
13
1S
0[
1s
0{
#249
#249
#250
#250
03
1;
0C
1[
15!
1M!
#251
#251
#252
#252
#253
#253
0#
1+
13
0;
1C
1K
0S
0[
1k
0s
05!
0M!
#254
#254
0+
03
0C
1S
1[
1c
0k
#255
#255
1#
1;
0K
0c
1s
15!
1M!
#256
#256
#257
#257
0#
1+
13
0;
1C
1K
0S
0[
1k
0s
05!
0M!
#258
#258
0+
1;
0C
1S
1c
0k
1%!
1E!
#259
#259
1+
03
0S
1[
0c
1k
0%!
1-!
#260
#260
1#
0+
0K
1S
0k
1s
0-!
15!
0E!
1M!
#261
#261
#262
#262
0#
1+
1K
0S
1k
0s
1-!
05!
1E!
0M!
#263
#263
0+
0;
1S
1c
0k
0-!
0E!
#264
#264
1#
1;
0K
0c
1s
15!
1M!
#265
#265
1+
0;
1C
0S
0s
1{
05!
0M!
#266
#266
0+
1;
0C
1S
1s
0{
15!
1M!
#267
#267
0#
13
1K
0[
1c
0s
1%!
05!
1E!
0M!
#268
#268
1#
1+
1C
0K
0S
0c
1{
0%!
1=!
0E!
1M!
#269
#269
03
0;
1[
0=!
0M!
#270
#270
0+
13
1S
0[
1s
0{
#271
#271
1+
1;
0S
0s
1{
1=!
1M!
#272
#272
03
0;
1[
0=!
0M!
#273
#273
0#
1;
0C
1K
1k
0{
1-!
1E!
#274
#274
0+
0;
1S
1c
0k
0-!
0E!
#275
#275
1+
1;
0S
0c
1k
1-!
1E!
#276
#276
#277
#277
1#
13
1C
0K
0[
0k
1{
0-!
1=!
0E!
1M!
#278
#278
0#
0+
03
0;
0C
1K
1S
1[
1c
0{
0=!
0M!
#279
#279
1+
13
1C
0S
0[
0c
1k
#280
#280
0+
1;
0C
1S
1c
0k
1%!
1E!
#281
#281
1#
1+
03
0;
1C
0K
0S
1[
0c
1{
0%!
0E!
#282
#282
0#
1;
0C
1K
1k
0{
1-!
1E!
#283
#283
1#
13
1C
0K
0[
0k
1{
0-!
1=!
0E!
1M!
#284
#284
03
0;
1[
0=!
0M!
#285
#285
0#
13
1K
0[
1k
0{
#286
#286
03
1;
0C
1[
1-!
1E!
#287
#287
0+
13
1S
0[
1c
0k
1%!
0-!
#288
#288
1#
1+
03
0;
1C
0K
0S
1[
0c
1{
0%!
0E!
#289
#289
13
1;
0[
1=!
1M!
#290
#290
0#
03
0C
1K
1[
1k
0{
1-!
0=!
1E!
0M!
#291
#291
1#
13
1C
0K
0[
0k
1{
0-!
1=!
0E!
1M!
#292
#292
0#
03
0C
1K
1[
1k
0{
1-!
0=!
1E!
0M!
#293
#293
0+
13
1S
0[
1c
0k
1%!
0-!
#294
#294
1#
03
0K
1[
0c
1s
0%!
15!
0E!
1M!
#295
#295
13
0;
1C
0[
05!
0M!
#296
#296
#297
#297
#298
#298
03
1;
0C
1[
15!
1M!
#299
#299
1+
13
1C
0S
0[
0s
1{
05!
1=!
#300
#300
0#
0+
0C
1K
1S
1c
0{
1%!
0=!
1E!
0M!
#301
#301
1+
03
0S
1[
0c
1k
0%!
1-!
#302
#302
13
0;
1C
0[
0-!
0E!
#303
#303
03
1;
0C
1[
1-!
1E!
#304
#304
#305
#305
0+
0;
1S
1c
0k
0-!
0E!
#306
#306
1+
1;
0S
0c
1k
1-!
1E!
#307
#307
1#
0;
1C
0K
0k
1{
0-!
0E!
#308
#308
0#
0+
0C
1K
1S
1c
0{
#309
#309
1#
1+
1C
0K
0S
0c
1{
#310
#310
0#
1;
0C
1K
1k
0{
1-!
1E!
#311
#311
1#
0+
13
0;
1C
0K
1S
0[
0k
1s
0-!
0E!
#312
#312
#313
#313
03
1;
0C
1[
15!
1M!
#314
#314
13
0;
1C
0[
05!
0M!
#315
#315
1+
03
0S
1[
0s
1{
#316
#316
13
1;
0[
1=!
1M!
#317
#317
0+
03
0C
1S
1[
1s
0{
15!
0=!
#318
#318
#319
#319
0#
1+
13
0;
1C
1K
0S
0[
1k
0s
05!
0M!
#320
#320
0+
1;
0C
1S
1c
0k
1%!
1E!
#321
#321
1+
0;
1C
0S
0c
1k
0%!
0E!
#322
#322
1#
1;
0K
0k
1{
1=!
1M!
#323
#323
0#
0+
0C
1K
1S
1c
0{
1%!
0=!
1E!
0M!
#324
#324
1#
1+
03
0;
1C
0K
0S
1[
0c
1{
0%!
0E!
#325
#325
0#
0+
13
1;
0C
1K
1S
0[
1c
0{
1%!
1E!
#326
#326
1+
03
0S
1[
0c
1k
0%!
1-!
#327
#327
0+
0;
1S
1c
0k
0-!
0E!
#328
#328
1+
1;
0S
0c
1k
1-!
1E!
#329
#329
1#
0;
1C
0K
0k
1{
0-!
0E!
#330
#330
0#
1;
0C
1K
1k
0{
1-!
1E!
#331
#331
1#
13
1C
0K
0[
0k
1{
0-!
1=!
0E!
1M!
#332
#332
0#
03
0C
1K
1[
1k
0{
1-!
0=!
1E!
0M!
#333
#333
1#
0;
1C
0K
0k
1{
0-!
0E!
#334
#334
0+
13
1S
0[
1s
0{
#335
#335
1+
1;
0S
0s
1{
1=!
1M!
#336
#336
0#
03
0C
1K
1[
1k
0{
1-!
0=!
1E!
0M!
#337
#337
#338
#338
0+
0;
1S
1c
0k
0-!
0E!
#339
#339
1+
13
1C
0S
0[
0c
1k
#340
#340
#341
#341
03
1;
0C
1[
1-!
1E!
#342
#342
13
0;
1C
0[
0-!
0E!
#343
#343
#344
#344
1#
0+
0K
1S
0k
1s
#345
#345
0#
1+
03
1;
0C
1K
0S
1[
1k
0s
1-!
1E!
#346
#346
#347
#347
13
0;
1C
0[
0-!
0E!
#348
#348
1#
1;
0K
0k
1{
1=!
1M!
#349
#349
03
0;
1[
0=!
0M!
#350
#350
0#
0+
0C
1K
1S
1c
0{
#351
#351
1#
13
1C
0K
0[
0c
1s
#352
#352
0#
03
0C
1K
1[
1c
0s
#353
#353
1#
1+
13
1;
1C
0K
0S
0[
0c
1{
1=!
1M!
#354
#354
0#
0+
0C
1K
1S
1c
0{
1%!
0=!
1E!
0M!
#355
#355
03
0;
1[
0%!
0E!
#356
#356
13
1;
0[
1%!
1E!
#357
#357
1+
03
0S
1[
0c
1k
0%!
1-!
#358
#358
0+
13
1S
0[
1c
0k
1%!
0-!
#359
#359
1#
1+
1C
0K
0S
0c
1{
0%!
1=!
0E!
1M!
#360
#360
0#
0;
1K
1k
0{
0=!
0M!
#361
#361
#362
#362
1#
03
0K
1[
0k
1{
#363
#363
0+
13
1S
0[
1s
0{
#364
#364
1+
1;
0S
0s
1{
1=!
1M!
#365
#365
0#
0;
1K
1k
0{
0=!
0M!
#366
#366
1#
03
0K
1[
0k
1{
#367
#367
0#
0+
13
1;
0C
1K
1S
0[
1c
0{
1%!
1E!
#368
#368
1#
0;
1C
0K
0c
1s
0%!
0E!
#369
#369
0#
1+
03
1;
0C
1K
0S
1[
1k
0s
1-!
1E!
#370
#370
1#
13
1C
0K
0[
0k
1{
0-!
1=!
0E!
1M!
#371
#371
0#
03
0C
1K
1[
1k
0{
1-!
0=!
1E!
0M!
#372
#372
0+
13
1S
0[
1c
0k
1%!
0-!
#373
#373
03
0;
1[
0%!
0E!
#374
#374
1#
1+
13
1;
1C
0K
0S
0[
0c
1{
1=!
1M!
#375
#375
0#
03
0C
1K
1[
1k
0{
1-!
0=!
1E!
0M!
#376
#376
1#
0+
13
0;
1C
0K
1S
0[
0k
1s
0-!
0E!
#377
#377
1+
1;
0S
0s
1{
1=!
1M!
#378
#378
0#
0+
0C
1K
1S
1c
0{
1%!
0=!
1E!
0M!
#379
#379
1#
0;
1C
0K
0c
1s
0%!
0E!
#380
#380
03
1;
0C
1[
15!
1M!
#381
#381
#382
#382
#383
#383
#384
#384
1+
13
1C
0S
0[
0s
1{
05!
1=!
#385
#385
0#
0;
1K
1k
0{
0=!
0M!
#386
#386
#387
#387
1#
0+
03
1;
0C
0K
1S
1[
0k
1s
15!
1M!
#388
#388
1+
0;
1C
0S
0s
1{
05!
0M!
#389
#389
0#
0+
13
1;
0C
1K
1S
0[
1c
0{
1%!
1E!
#390
#390
1#
0;
1C
0K
0c
1s
0%!
0E!
#391
#391
0#
1+
1K
0S
1k
0s
#392
#392
0+
03
0C
1S
1[
1c
0k
#393
#393
1+
1;
0S
0c
1k
1-!
1E!
#394
#394
1#
0+
0K
1S
0k
1s
0-!
15!
0E!
1M!
#395
#395
0#
13
1K
0[
1c
0s
1%!
05!
1E!
0M!
#396
#396
1#
03
0K
1[
0c
1s
0%!
15!
0E!
1M!
#397
#397
13
0;
1C
0[
05!
0M!
#398
#398
1+
03
0S
1[
0s
1{
#399
#399
0#
1;
0C
1K
1k
0{
1-!
1E!
#400
#400
1#
0;
1C
0K
0k
1{
0-!
0E!
#401
#401
0#
13
1K
0[
1k
0{
#402
#402
1#
03
0K
1[
0k
1{
#403
#403
13
1;
0[
1=!
1M!
#404
#404
0#
0+
03
0;
0C
1K
1S
1[
1c
0{
0=!
0M!
#405
#405
1+
1;
0S
0c
1k
1-!
1E!
#406
#406
1#
0+
13
0;
1C
0K
1S
0[
0k
1s
0-!
0E!
#407
#407
0#
1+
1K
0S
1k
0s
#408
#408
1#
03
0K
1[
0k
1{
#409
#409
13
1;
0[
1=!
1M!
#410
#410
0+
03
0C
1S
1[
1s
0{
15!
0=!
#411
#411
0#
13
1K
0[
1c
0s
1%!
05!
1E!
0M!
#412
#412
1#
1+
03
0;
1C
0K
0S
1[
0c
1{
0%!
0E!
#413
#413
#414
#414
#415
#415
13
1;
0[
1=!
1M!
#416
#416
0+
03
0C
1S
1[
1s
0{
15!
0=!
#417
#417
0#
13
1K
0[
1c
0s
1%!
05!
1E!
0M!
#418
#418
1#
1+
03
0;
1C
0K
0S
1[
0c
1{
0%!
0E!
#419
#419
0+
13
1S
0[
1s
0{
#420
#420
#421
#421
#422
#422
1+
1;
0S
0s
1{
1=!
1M!
#423
#423
03
0;
1[
0=!
0M!
#424
#424
0+
13
1S
0[
1s
0{
#425
#425
0#
1+
03
1;
0C
1K
0S
1[
1k
0s
1-!
1E!
#426
#426
1#
0+
0K
1S
0k
1s
0-!
15!
0E!
1M!
#427
#427
1+
13
1C
0S
0[
0s
1{
05!
1=!
#428
#428
0+
03
0C
1S
1[
1s
0{
15!
0=!
#429
#429
13
0;
1C
0[
05!
0M!
#430
#430
1+
1;
0S
0s
1{
1=!
1M!
#431
#431
0#
0+
0C
1K
1S
1c
0{
1%!
0=!
1E!
0M!
#432
#432
1+
03
0S
1[
0c
1k
0%!
1-!
#433
#433
1#
13
1C
0K
0[
0k
1{
0-!
1=!
0E!
1M!
#434
#434
0+
0;
1S
1s
0{
0=!
0M!
#435
#435
0#
03
0C
1K
1[
1c
0s
#436
#436
13
1;
0[
1%!
1E!
#437
#437
1+
03
0S
1[
0c
1k
0%!
1-!
#438
#438
1#
0+
0K
1S
0k
1s
0-!
15!
0E!
1M!
#439
#439
0#
0;
1K
1c
0s
05!
0M!
#440
#440
1#
1+
13
1;
1C
0K
0S
0[
0c
1{
1=!
1M!
#441
#441
0#
03
0C
1K
1[
1k
0{
1-!
0=!
1E!
0M!
#442
#442
1#
13
1C
0K
0[
0k
1{
0-!
1=!
0E!
1M!
#443
#443
0+
03
0C
1S
1[
1s
0{
15!
0=!
#444
#444
1+
13
1C
0S
0[
0s
1{
05!
1=!
#445
#445
0#
0;
1K
1k
0{
0=!
0M!
#446
#446
1#
1;
0K
0k
1{
1=!
1M!
#447
#447
0#
0+
0C
1K
1S
1c
0{
1%!
0=!
1E!
0M!
#448
#448
1+
0;
1C
0S
0c
1k
0%!
0E!
#449
#449
#450
#450
1#
0+
03
1;
0C
0K
1S
1[
0k
1s
15!
1M!
#451
#451
0#
0;
1K
1c
0s
05!
0M!
#452
#452
1+
13
1C
0S
0[
0c
1k
#453
#453
03
1;
0C
1[
1-!
1E!
#454
#454
0+
13
1S
0[
1c
0k
1%!
0-!
#455
#455
1#
0;
1C
0K
0c
1s
0%!
0E!
#456
#456
1+
03
0S
1[
0s
1{
#457
#457
0#
1;
0C
1K
1k
0{
1-!
1E!
#458
#458
1#
0;
1C
0K
0k
1{
0-!
0E!
#459
#459
0+
13
1S
0[
1s
0{
#460
#460
0#
1+
03
1;
0C
1K
0S
1[
1k
0s
1-!
1E!
#461
#461
1#
0;
1C
0K
0k
1{
0-!
0E!
#462
#462
0+
1;
0C
1S
1s
0{
15!
1M!
#463
#463
0#
13
1K
0[
1c
0s
1%!
05!
1E!
0M!
#464
#464
#465
#465
#466
#466
1#
1+
1C
0K
0S
0c
1{
0%!
1=!
0E!
1M!
#467
#467
03
0;
1[
0=!
0M!
#468
#468
0#
1;
0C
1K
1k
0{
1-!
1E!
#469
#469
0+
0;
1S
1c
0k
0-!
0E!
#470
#470
1#
13
1C
0K
0[
0c
1s
#471
#471
1+
03
0S
1[
0s
1{
#472
#472
0#
0+
0C
1K
1S
1c
0{
#473
#473
1+
1;
0S
0c
1k
1-!
1E!
#474
#474
1#
13
1C
0K
0[
0k
1{
0-!
1=!
0E!
1M!
#475
#475
0#
0;
1K
1k
0{
0=!
0M!
#476
#476
1#
0+
03
1;
0C
0K
1S
1[
0k
1s
15!
1M!
#477
#477
0#
13
1K
0[
1c
0s
1%!
05!
1E!
0M!
#478
#478
1#
03
0K
1[
0c
1s
0%!
15!
0E!
1M!
#479
#479
#480
#480
1+
13
1C
0S
0[
0s
1{
05!
1=!
#481
#481
0#
03
0C
1K
1[
1k
0{
1-!
0=!
1E!
0M!
#482
#482
13
0;
1C
0[
0-!
0E!
#483
#483
1#
03
0K
1[
0k
1{
#484
#484
0+
13
1S
0[
1s
0{
#485
#485
0#
1;
0C
1K
1c
0s
1%!
1E!
#486
#486
1#
1+
1C
0K
0S
0c
1{
0%!
1=!
0E!
1M!
#487
#487
0+
0;
1S
1s
0{
0=!
0M!
#488
#488
1+
1;
0S
0s
1{
1=!
1M!
#489
#489
0+
0;
1S
1s
0{
0=!
0M!
#490
#490
0#
1+
1K
0S
1k
0s
#491
#491
1#
03
0K
1[
0k
1{
#492
#492
13
1;
0[
1=!
1M!
#493
#493
0#
0+
03
0;
0C
1K
1S
1[
1c
0{
0=!
0M!
#494
#494
#495
#495
#496
#496
1#
13
1C
0K
0[
0c
1s
#497
#497
0#
1+
1K
0S
1k
0s
#498
#498
0+
03
0C
1S
1[
1c
0k
#499
#499
1#
1;
0K
0c
1s
15!
1M!
#500
